flask_api_sign/__init__.py
flask_api_sign/api_sign_manager.py
flask_api_sign/config.py
flask_api_sign/exceptions.py
flask_api_sign/utils.py
flask_api_sign/view_decorators.py
flask_api_sign-0.1.1.dist-info/AUTHORS.rst
flask_api_sign-0.1.1.dist-info/LICENSE
flask_api_sign-0.1.1.dist-info/METADATA
flask_api_sign-0.1.1.dist-info/WHEEL
flask_api_sign-0.1.1.dist-info/entry_points.txt
flask_api_sign-0.1.1.dist-info/top_level.txt
flask_api_sign-0.1.1.dist-info/RECORD
