Metadata-Version: 2.1
Name: flask-api-sign
Version: 0.1.1
Summary: Flask extension of Api sign Verification
Home-page: https://github.com/juforg/flask-api-sign
Author: juforg
Author-email: juforg@gmail.com
License: MIT license
Keywords: flask,api,sign,auth,verification,flask_api_sign
Platform: UNKNOWN
Classifier: Development Status :: 3 - Alpha
Classifier: Intended Audience :: Developers
Classifier: License :: OSI Approved :: MIT License
Classifier: Natural Language :: English
Classifier: Natural Language :: Chinese (Simplified)
Classifier: Environment :: Plugins
Classifier: Framework :: Flask
Classifier: Programming Language :: Python :: 3
Classifier: Programming Language :: Python :: 3.3
Classifier: Programming Language :: Python :: 3.4
Classifier: Programming Language :: Python :: 3.5
Classifier: Programming Language :: Python :: 3.7
Classifier: Programming Language :: Python :: 3.8
Classifier: Programming Language :: Python :: 3.9
Classifier: Topic :: Internet :: WWW/HTTP :: Dynamic Content
Classifier: Topic :: Software Development :: Libraries :: Python Modules
Classifier: Operating System :: Microsoft :: Windows
Classifier: Operating System :: POSIX :: Linux
Classifier: Operating System :: POSIX
Classifier: Operating System :: Unix
Classifier: Operating System :: MacOS
License-File: LICENSE
License-File: AUTHORS.rst
Requires-Dist: Click (>=6.0)
Requires-Dist: Flask (>=1.0)
